{
	"class" : {
		 },
	"instance" : {
		"initialize" : "HernanMoralesDurand 12/19/2013 23:28",
		"isValidIpAddress:" : "HernanMoralesDurand 3/3/2014 03:51",
		"isValidPeer:" : "HernanMoralesDurand 11/26/2013 18:05",
		"loginAdminNamed:password:machine:" : "HernanMoralesDurand 3/3/2014 03:52",
		"loginUserNamed:password:machine:" : "HernanMoralesDurand 3/3/2014 03:52",
		"removeRepository" : "HernanMoralesDurand 10/13/2014 18:08",
		"repository" : "HernanMoralesDurand 12/20/2013 00:58",
		"resetStatus" : "HernanMoralesDurand 12/19/2013 23:28",
		"stats" : "HernanMoralesDurand 11/13/2013 03:00",
		"updateRepositoryStats" : "HernanMoralesDurand 12/20/2013 01:16",
		"userByEmail:" : "HernanMoralesDurand 12/23/2013 21:41",
		"validatePassword:forUser:" : "HernanMoralesDurand 1/17/2014 05:44",
		"verifyPassword:forUser:" : "HernanMoralesDurand 12/10/2013 19:52",
		"wantsToWriteLog" : "HernanMoralesDurand 10/27/2013 18:32" } }
